uvm_tb_gen/__init__.py
uvm_tb_gen/agent_pkg.py
uvm_tb_gen/environment_pkg.py
uvm_tb_gen/interface.py
uvm_tb_gen/run.py
uvm_tb_gen/tb_config.py
uvm_tb_gen/test_pkg.py
uvm_tb_gen/top_module.py
uvm_tb_gen/uvm_component.py
uvm_tb_gen/uvm_object.py
uvm_tb_gen-0.1.4.dist-info/METADATA
uvm_tb_gen-0.1.4.dist-info/WHEEL
uvm_tb_gen-0.1.4.dist-info/entry_points.txt
uvm_tb_gen-0.1.4.dist-info/top_level.txt
uvm_tb_gen-0.1.4.dist-info/RECORD
