Metadata-Version: 2.4
Name: uvm_tb_gen
Version: 0.1.4
Summary: An automation tool that generates complete UVM testbench infrastructure with dynamic configuration for interfaces, agents, environments, and tests.
Author: Vinay Kumar Kadirika
Keywords: UVM,SystemVerilog,Verification,VLSI,EDA,Testbench,Automation
Classifier: Programming Language :: Python :: 3
Classifier: Programming Language :: Python :: 3 :: Only
Classifier: Operating System :: POSIX :: Linux
Classifier: Topic :: Software Development :: Code Generators
Classifier: Topic :: Scientific/Engineering :: Electronic Design Automation (EDA)
Classifier: Intended Audience :: Developers
Classifier: Intended Audience :: Science/Research
Requires-Python: >=3.8
